stock_summary/__init__.py
stock_summary/demo_datasets/dividends
stock_summary/demo_datasets/entries
stock_summary/demo_datasets/index.html
stock_summary/demo_datasets/main.css
stock_summary/demo_datasets/portfolio
stock_summary/html_files/jinja.html
stock_summary/html_files/main.css
stock_summary/init_datasets/dividends
stock_summary/init_datasets/entries
stock_summary/init_datasets/portfolio
stock_summary/library.py
stock_summary/main.py
stock_summary/parsers.py
stock_summary/settings.py
stock_summary_tool-0.1.1.dist-info/METADATA
stock_summary_tool-0.1.1.dist-info/entry_points.txt
stock_summary_tool-0.1.1.dist-info/WHEEL
stock_summary_tool-0.1.1.dist-info/RECORD
