Metadata-Version: 2.1
Name: stock-summary-tool
Version: 0.1.1
Summary: Tool for tracking of your investments and your actual portfolio
Author: Simon Foucek
Author-email: foucek.simon@gmail.com
Requires-Python: >=3.8,<3.12
Classifier: Programming Language :: Python :: 3
Classifier: Programming Language :: Python :: 3.8
Classifier: Programming Language :: Python :: 3.9
Classifier: Programming Language :: Python :: 3.10
Classifier: Programming Language :: Python :: 3.11
Requires-Dist: appdirs (>=1.4.4,<2.0.0)
Requires-Dist: jinja2 (>=3.1.2,<4.0.0)
Requires-Dist: pandas (>=1.5.2,<2.0.0)
Requires-Dist: plotly (>=5.11.0,<6.0.0)
Requires-Dist: requests (>=2.28.1,<3.0.0)
